{
  "id": 22,
  "name": "Made-With-ML",
  "category": "ai-tools",
  "repo": "https://github.com/GokuMohandas/Made-With-ML.git",
  "stars": 48323,
  "license": "MIT",
  "maintainer": "GokuMohandas",
  "slug": "madewithml-guide",
  "date": "2026-06-22",
  "language": "en",
  "word_count": 3249,
  "h2_count": 10,
  "code_blocks": 21,
  "faq_count": 7,
  "image_count": 1,
  "comparison_table": true,
  "affiliate_links": [],
  "images": [
    {
      "url": "https://raw.githubusercontent.com/GokuMohandas/Made-With-ML/main/docs/logo.png",
      "alt": "Made With ML Logo"
    }
  ],
  "file_path": "/root/HERMES/articles/Made-With-ML/en.md"
}